nsync/__init__.py
nsync/test_nsync.py
nsync-0.0.1.dist-info/METADATA
nsync-0.0.1.dist-info/WHEEL
nsync-0.0.1.dist-info/top_level.txt
nsync-0.0.1.dist-info/RECORD
